MANIFEST.in
setup.py
avi/__init__.py
avi/netscaler_converter/__init__.py
avi/netscaler_converter/command_status.yaml
avi/netscaler_converter/csvs_converter.py
avi/netscaler_converter/lbvs_converter.py
avi/netscaler_converter/monitor_converter.py
avi/netscaler_converter/netscaler_config_converter.py
avi/netscaler_converter/netscaler_converter.py
avi/netscaler_converter/netscaler_parser.py
avi/netscaler_converter/ns_constants.py
avi/netscaler_converter/ns_service_converter.py
avi/netscaler_converter/ns_util.py
avi/netscaler_converter/policy_converter.py
avi/netscaler_converter/profile_converter.py
avi/netscaler_converter/scp_util.py
avi/netscaler_converter/setup.py
avi/netscaler_converter/upload_config.py
avi/netscaler_converter/output/Output.json
avi/netscaler_converter/test/__init__.py
avi/netscaler_converter/test/ns.conf
avi/netscaler_converter/test/test_lbvs_converter.cfg
avi/netscaler_converter/test/test_lbvs_converter.py
avi/netscaler_converter/test/test_monitor_converter.cfg
avi/netscaler_converter/test/test_monitor_converter.py
avi/netscaler_converter/test/test_ns_converter.py
avi/netscaler_converter/test/test_ns_service_converter.cfg
avi/netscaler_converter/test/test_ns_service_converter.py
avi/netscaler_converter/test/test_policy_converter.cfg
avi/netscaler_converter/test/test_policy_converter.py
avi/netscaler_converter/test/test_profile_converter.cfg
avi/netscaler_converter/test/test_profile_converter.py
avi/netscaler_converter/test/input_files/CD.cert.key
avi/netscaler_converter/test/input_files/ns-server.key
avi/netscaler_converter/test/input_files/test1.key
avinetscalerconverter.egg-info/PKG-INFO
avinetscalerconverter.egg-info/SOURCES.txt
avinetscalerconverter.egg-info/dependency_links.txt
avinetscalerconverter.egg-info/requires.txt
avinetscalerconverter.egg-info/top_level.txt
debian/__init__.py
debian/update_version.py