Metadata-Version: 1.1
Name: avinetscalerconverter
Version: 16.3.5.post1
Summary: Avi Netscaler Converter.
Home-page: http://avinetworks.com/
Author: Avi Networks
Author-email: support@avinetworks.com
License: UNKNOWN
Platform: UNKNOWN
Classifier: Operating System :: OS Independent
Classifier: Programming Language :: Python
Classifier: Programming Language :: Python :: 2.7
Classifier: Topic :: Internet :: WWW/HTTP
Classifier: Topic :: Internet :: WWW/HTTP :: Dynamic Content
